{"version":"6.0.0-rc4","objects":[{"cropX":0,"cropY":0,"id":"54f98017-339f-407d-9dab-aab139ad8ee9","erasable":true,"type":"Image","version":"6.0.0-rc4","originX":"left","originY":"top","left":377,"top":145,"width":1536,"height":2048,"fill":"rgb(0,0,0)","stroke":null,"strokeWidth":0,"strokeDashArray":null,"strokeLineCap":"butt","strokeDashOffset":0,"strokeLineJoin":"miter","strokeUniform":false,"strokeMiterLimit":4,"scaleX":0.1559,"scaleY":0.1559,"angle":0,"flipX":false,"flipY":false,"opacity":1,"shadow":null,"visible":true,"backgroundColor":"","fillRule":"nonzero","paintFirst":"fill","globalCompositeOperation":"source-over","skewX":0,"skewY":0,"src":"https://localhost:5173/uploadedFiles/canvasAssets/ead2c2a1-1930-4cba-a878-8768f2416684/oryg.jpg","crossOrigin":null,"filters":[]},{"cropX":0,"cropY":0,"id":"822cdb49-f353-4323-b383-9aab9fa9aa62","erasable":true,"type":"Image","version":"6.0.0-rc4","originX":"left","originY":"top","left":67,"top":144,"width":680,"height":364,"fill":"rgb(0,0,0)","stroke":null,"strokeWidth":0,"strokeDashArray":null,"strokeLineCap":"butt","strokeDashOffset":0,"strokeLineJoin":"miter","strokeUniform":false,"strokeMiterLimit":4,"scaleX":0.3522,"scaleY":0.3522,"angle":0,"flipX":false,"flipY":false,"opacity":1,"shadow":null,"visible":true,"backgroundColor":"","fillRule":"nonzero","paintFirst":"fill","globalCompositeOperation":"source-over","skewX":0,"skewY":0,"src":"https://localhost:5173/uploadedFiles/canvasAssets/ead2c2a1-1930-4cba-a878-8768f2416684/22.05.2025_21.11.59_REC.png","crossOrigin":null,"filters":[]},{"fontSize":20,"fontWeight":"normal","fontFamily":"Times New Roman","fontStyle":"normal","lineHeight":1.16,"text":"fdggdgdf","charSpacing":0,"textAlign":"left","styles":[],"pathStartOffset":0,"pathSide":"left","pathAlign":"baseline","underline":false,"overline":false,"linethrough":false,"textBackgroundColor":"","direction":"ltr","minWidth":20,"splitByGrapheme":false,"id":"a64281e6-4eb3-4b1e-8c0c-2934ca48f5aa","erasable":true,"type":"Textbox","version":"6.0.0-rc4","originX":"left","originY":"top","left":600,"top":513.75,"width":300,"height":22.6,"fill":"#000000","stroke":null,"strokeWidth":1,"strokeDashArray":null,"strokeLineCap":"butt","strokeDashOffset":0,"strokeLineJoin":"miter","strokeUniform":false,"strokeMiterLimit":4,"scaleX":1,"scaleY":1,"angle":0,"flipX":false,"flipY":false,"opacity":1,"shadow":null,"visible":true,"backgroundColor":"","fillRule":"nonzero","paintFirst":"fill","globalCompositeOperation":"source-over","skewX":0,"skewY":0}],"background":"#ffffff"}