{"version":"6.0.0-rc4","objects":[{"id":"44fdefe0-4ac9-11f0-b196-3bfdad2f1173","erasable":true,"type":"Path","version":"6.0.0-rc4","originX":"left","originY":"top","left":318.499,"top":155.249,"width":21.002,"height":23.002,"fill":null,"stroke":"rgb(0, 0, 0)","strokeWidth":1,"strokeDashArray":null,"strokeLineCap":"round","strokeDashOffset":0,"strokeLineJoin":"round","strokeUniform":false,"strokeMiterLimit":10,"scaleX":1,"scaleY":1,"angle":0,"flipX":false,"flipY":false,"opacity":1,"shadow":null,"visible":true,"backgroundColor":"","fillRule":"nonzero","paintFirst":"fill","globalCompositeOperation":"source-over","skewX":0,"skewY":0,"path":[["M",340.001,155.749],["Q",340,155.75,339,157.75],["Q",338,159.75,337.5,160.25],["Q",337,160.75,336.5,160.75],["Q",336,160.75,336,161.25],["Q",336,161.75,335.5,162.25],["Q",335,162.75,334.5,163.25],["Q",334,163.75,333.5,164.25],["Q",333,164.75,332.5,165.25],["Q",332,165.75,331.5,165.75],["Q",331,165.75,331,166.25],["Q",331,166.75,330,167.25],["Q",329,167.75,328.5,168.25],["Q",328,168.75,327.5,169.25],["Q",327,169.75,323,174.25],["L",318.999,178.751]]}],"background":"#ffffff"}