{"version":"6.0.0-rc4","objects":[{"cropX":0,"cropY":0,"id":"2dacd6fc-fd28-4805-9c0c-ee58fe8b5e4a","erasable":true,"type":"Image","version":"6.0.0-rc4","originX":"left","originY":"top","left":0,"top":0,"width":1536,"height":2048,"fill":"rgb(0,0,0)","stroke":null,"strokeWidth":0,"strokeDashArray":null,"strokeLineCap":"butt","strokeDashOffset":0,"strokeLineJoin":"miter","strokeUniform":false,"strokeMiterLimit":4,"scaleX":0.0934,"scaleY":0.0934,"angle":0,"flipX":false,"flipY":false,"opacity":1,"shadow":null,"visible":true,"backgroundColor":"","fillRule":"nonzero","paintFirst":"fill","globalCompositeOperation":"source-over","skewX":0,"skewY":0,"src":"https://localhost:5173/uploadedFiles/canvasAssets/6426a5d1-c9f0-4ace-b574-d9612cf460e6/oryg.jpg","crossOrigin":null,"filters":[]}],"background":"#ffffff"}